mmgmt/__init__.py
mmgmt/__main__.py
mmgmt/aws.py
mmgmt/cli.py
mmgmt/config.py
mmgmt/utils.py
mmgmt-0.5.3.dist-info/LICENSE
mmgmt-0.5.3.dist-info/METADATA
mmgmt-0.5.3.dist-info/WHEEL
mmgmt-0.5.3.dist-info/entry_points.txt
mmgmt-0.5.3.dist-info/RECORD
